<?xml version="1.0" encoding="utf-8"?>
<rdf:RDF
        xmlns:skos="http://www.w3.org/2004/02/skos/core#"
        xmlns:rdf="http://www.w3.org/1999/02/22-rdf-syntax-ns#"
>
    <skos:Collection rdf:about="http://localhost:8000/33eb1163-f29f-4dba-9d51-d191574dfda2">
        <skos:member>
            <skos:Concept rdf:about="http://localhost:8000/10eb5d94-ef77-4d21-b120-896edcdee6c7"/>
        </skos:member>
        <skos:member>
            <skos:Concept rdf:about="http://localhost:8000/7fa59c62-acf8-4fed-84c0-ed171c2bbe70"/>
        </skos:member>
        <skos:member>
            <skos:Concept rdf:about="http://localhost:8000/9a3241c4-b376-40ce-ba70-281fa3baf996"/>
        </skos:member>
        <skos:member>
            <skos:Concept rdf:about="http://localhost:8000/445e3f51-be88-4c19-ac1d-6a871f5b9c18"/>
        </skos:member>
        <skos:member>
            <skos:Concept rdf:about="http://localhost:8000/f7ee7ebb-e764-4142-864c-6e697467464b"/>
        </skos:member>
        <skos:prefLabel xml:lang="en">{"id": "095e015e-d091-4ac6-bb36-b87d6f1dcb9b", "value": "Description Type"}</skos:prefLabel>
        <skos:member>
            <skos:Concept rdf:about="http://localhost:8000/28c3b483-9204-4baa-bdb9-252e0647054e"/>
        </skos:member>
        <skos:member>
            <skos:Concept rdf:about="http://localhost:8000/f1cbae8f-0090-47dc-8252-ee533a2deb29"/>
        </skos:member>
    </skos:Collection>
    <skos:Collection rdf:about="http://localhost:8000/99e79f19-ef50-46a8-847d-08ce47ce912a">
        <skos:member>
            <skos:Concept rdf:about="http://localhost:8000/217c0b17-bf8c-433e-b8b0-e8c6746701c9"/>
        </skos:member>
        <skos:member>
            <skos:Concept rdf:about="http://localhost:8000/c0e7b324-95fb-4f9c-97d1-575291b211bd"/>
        </skos:member>
        <skos:prefLabel xml:lang="en">{"id": "ab10d42a-7206-41f0-8bb0-23a9e4414dd8", "value": "Taxonomic Rank"}</skos:prefLabel>
        <skos:scopeNote xml:lang="en">{"id": "4ff978c2-5ea2-438b-9981-9c320e975563", "value": "Taxonomic Rank of the name (scientific names only)"}</skos:scopeNote>
    </skos:Collection>
    <skos:Collection rdf:about="http://localhost:8000/7d13e6cd-6b98-4886-b574-05a1e109dd67">
        <skos:member>
            <skos:Concept rdf:about="http://localhost:8000/e18f67b9-71e5-4dbb-ac41-63263aebe734"/>
        </skos:member>
        <skos:prefLabel xml:lang="en">{"id": "718563c9-1518-4e25-9308-3e82a72ca3d3", "value": "Fossil Size Category"}</skos:prefLabel>
        <skos:member>
            <skos:Concept rdf:about="http://localhost:8000/8a7e10ab-a0e9-4d00-b66a-270c3cacff2a"/>
        </skos:member>
    </skos:Collection>
    <skos:Collection rdf:about="http://localhost:8000/54d7bcc0-b6fd-4663-b281-6d3c27a802e5">
        <skos:member>
            <skos:Concept rdf:about="http://localhost:8000/8ac92afb-43eb-438a-8543-0037e3b88f40"/>
        </skos:member>
        <skos:prefLabel xml:lang="en">{"id": "e3b98628-3cf3-4d13-a787-7948841698b6", "value": "Languages"}</skos:prefLabel>
        <skos:member>
            <skos:Concept rdf:about="http://localhost:8000/670ab8c8-17cf-4802-8f09-f1cecf10def7"/>
        </skos:member>
        <skos:scopeNote xml:lang="en">{"id": "611a4885-71fe-4b13-861c-658604567c06", "value": "Languages that textual elements can be represented"}</skos:scopeNote>
    </skos:Collection>
    <skos:Collection rdf:about="http://localhost:8000/19f1c4e4-e545-48c5-8fb5-1d54c710cdf9">
        <skos:member>
            <skos:Concept rdf:about="http://localhost:8000/bb50b0cf-6665-4ba8-90f2-e4ca3dbe2b2b"/>
        </skos:member>
        <skos:member>
            <skos:Concept rdf:about="http://localhost:8000/94f4d957-4ab5-46c6-b725-9a678ef5cfa2"/>
        </skos:member>
        <skos:scopeNote xml:lang="en">{"id": "2c26eb57-e199-41d8-af2b-5ca384cf603a", "value": "Classification of notes associated with a Sample Fossil"}</skos:scopeNote>
        <skos:member>
            <skos:Concept rdf:about="http://localhost:8000/fdd8420c-f974-4ee2-9ac6-80527f000a95"/>
        </skos:member>
        <skos:member>
            <skos:Concept rdf:about="http://localhost:8000/7f149a9d-121a-41d9-8395-efc5c998bc09"/>
        </skos:member>
        <skos:member>
            <skos:Concept rdf:about="http://localhost:8000/685bec22-cde6-498c-9052-288022aa7988"/>
        </skos:member>
        <skos:member>
            <skos:Concept rdf:about="http://localhost:8000/2439c72d-fd9e-49c6-8c81-12b2f1f1fb6f"/>
        </skos:member>
        <skos:prefLabel xml:lang="en">{"id": "1a662a61-5cca-4623-866b-039458747e69", "value": "Fossil Sample Note Type"}</skos:prefLabel>
        <skos:member>
            <skos:Concept rdf:about="http://localhost:8000/6906cc1d-5517-4ff6-92bd-90ec8986dec8"/>
        </skos:member>
    </skos:Collection>
    <skos:Collection rdf:about="http://localhost:8000/00000000-0000-0000-0000-000000000005">
        <skos:member>
            <skos:Concept rdf:about="http://localhost:8000/00000000-0000-0000-0000-000000000007"/>
        </skos:member>
        <skos:prefLabel xml:lang="en-us">{"id": "d8c622f6-e786-11e6-905a-475a5eee86f5", "value": "Resource To Resource Relationship Types"}</skos:prefLabel>
    </skos:Collection>
    <skos:Collection rdf:about="http://localhost:8000/a979b729-9aa1-4aa6-877e-a61be5b83134">
        <skos:member>
            <skos:Concept rdf:about="http://localhost:8000/0464facd-9edc-482e-98d5-ac0243439005"/>
        </skos:member>
        <skos:prefLabel xml:lang="en">{"id": "9a4cc403-41a8-4b36-a2c2-d73f33b6a326", "value": "FRPC Ranking Code"}</skos:prefLabel>
        <skos:member>
            <skos:Concept rdf:about="http://localhost:8000/2b85ccb2-f8e3-4e43-b61d-ab5658805c05"/>
        </skos:member>
        <skos:member>
            <skos:Concept rdf:about="http://localhost:8000/bafdfae0-cd10-4ca2-9b48-2f09dbe9ad6a"/>
        </skos:member>
        <skos:member>
            <skos:Concept rdf:about="http://localhost:8000/f6d941d1-37d1-497c-9944-3edfc55d7aa4"/>
        </skos:member>
        <skos:member>
            <skos:Concept rdf:about="http://localhost:8000/9cb2571a-c30d-412c-9dd8-a1ddf29674ae"/>
        </skos:member>
    </skos:Collection>
    <skos:Collection rdf:about="http://localhost:8000/4ef99511-e7fe-4655-ad46-a1505c9b8999">
        <skos:member>
            <skos:Concept rdf:about="http://localhost:8000/25618cfe-b354-4c9c-9d1b-50dc64cff166"/>
        </skos:member>
        <skos:scopeNote xml:lang="en">{"id": "1da84206-5bb2-43c2-9689-585e31f40e2a", "value": "Types of notes for a BC Collection Event"}</skos:scopeNote>
        <skos:prefLabel xml:lang="en">{"id": "8f198243-201b-40c9-ac8d-f98095dc2f3f", "value": "Collection Event Note Type"}</skos:prefLabel>
        <skos:member>
            <skos:Concept rdf:about="http://localhost:8000/3bf6aed8-edbf-4210-9fb3-823bcb425ad3"/>
        </skos:member>
    </skos:Collection>
    <skos:Collection rdf:about="http://localhost:8000/4b28af7f-a6f1-4090-a945-c14b75809621">
        <skos:member>
            <skos:Concept rdf:about="http://localhost:8000/00f24b6d-4d90-3f6d-bdd3-aedcf61399dc">
                <skos:member rdf:resource="http://localhost:8000/18e4d5fe-955b-35b9-81f6-33bb14650f67"/>
                <skos:member rdf:resource="http://localhost:8000/ae352fec-08d0-3f04-a8cb-8b47fc5897dd"/>
                <skos:member rdf:resource="http://localhost:8000/e70e3c47-2eec-309f-92b9-9c0c4f049ee4"/>
            </skos:Concept>
        </skos:member>
        <skos:member>
            <skos:Concept rdf:about="http://localhost:8000/29aa334d-e03f-3fd1-a15a-a621f284764e">
                <skos:member rdf:resource="http://localhost:8000/f1d37da1-2534-3184-a360-c716bff3982e"/>
                <skos:member rdf:resource="http://localhost:8000/b1fabadc-7863-3081-8f40-556579978f85"/>
                <skos:member rdf:resource="http://localhost:8000/26842550-baa1-34ad-bce3-f58f350a0af6"/>
            </skos:Concept>
        </skos:member>
        <skos:prefLabel xml:lang="en">{"id": "9de75630-7dfb-4157-96c0-2fbf491723ce", "value": "Geologic Time Scale (2020)"}</skos:prefLabel>
        <skos:scopeNote xml:lang="en">{"id": "37c60613-a7c9-410b-967a-a3a8480fea89", "value": "RDF representation of the Geologic Time Scale, as defined in the International Chronostratigraphic Chart (ICC) from the International Commission on Stratigraphy (ICS). The ICC embraces both chronostratigraphic (time-rock) units and their equivalent geochronologic (geologic-time) units, the former being related to the \u2018Stratigraphic points\u2019 referred to below, and the latter (geochronologic units) being employed in this RDF representation."}</skos:scopeNote>
    </skos:Collection>
    <skos:Collection rdf:about="http://localhost:8000/8d33ccb2-9fca-4d3b-bf07-dd0f00adb52d">
        <skos:member>
            <skos:Concept rdf:about="http://localhost:8000/b8119044-a47c-4de0-8775-a738bb2d04a8"/>
        </skos:member>
        <skos:prefLabel xml:lang="en">{"id": "9bd2ad7f-27fd-44b6-8aaa-8cf86337fa89", "value": "Sample Storage Location Note Type"}</skos:prefLabel>
        <skos:member>
            <skos:Concept rdf:about="http://localhost:8000/c2890e57-4737-492f-a8bf-8277cb676441"/>
        </skos:member>
        <skos:scopeNote xml:lang="en">{"id": "3f3a695b-fce4-4dc0-ab1d-60471b1b343a", "value": "Types of notes used for Sample -&gt; Storage Location relationship"}</skos:scopeNote>
    </skos:Collection>
    <skos:Collection rdf:about="http://localhost:8000/79bb1dcf-733b-4a15-90ad-2c7144b80f5f">
        <skos:member>
            <skos:Concept rdf:about="http://localhost:8000/580ecbb1-fc32-4461-b77f-aaf285269ae1"/>
        </skos:member>
        <skos:member>
            <skos:Concept rdf:about="http://localhost:8000/1959353b-9985-4a51-be12-13978d3dbecf"/>
        </skos:member>
        <skos:prefLabel xml:lang="en">{"id": "ed38d61a-55b9-41f6-b1c3-a4b686d8995c", "value": "BC Fossil Name Type"}</skos:prefLabel>
    </skos:Collection>
    <skos:Concept rdf:about="http://localhost:8000/c63af19a-1b16-3059-82cb-2009204cecfa"/>
    <skos:Concept rdf:about="http://localhost:8000/a93e0e4b-6c50-301f-aa36-6645ad24b5cf"/>
    <skos:Concept rdf:about="http://localhost:8000/6d509fcc-b642-39d2-8961-2d867c4b4560">
        <skos:member>
            <skos:Concept rdf:about="http://localhost:8000/e16844ef-e265-397d-b99a-aff276492fb9">
                <skos:member rdf:resource="http://localhost:8000/7298ffc8-23ed-3a8e-85a0-27efb08a361e"/>
                <skos:member rdf:resource="http://localhost:8000/8581e5a7-08cf-3fc6-9f5c-54d0020718cd"/>
            </skos:Concept>
        </skos:member>
        <skos:member>
            <skos:Concept rdf:about="http://localhost:8000/53c370fe-4496-3d69-b055-423462bc4e97"/>
        </skos:member>
        <skos:member>
            <skos:Concept rdf:about="http://localhost:8000/1111ee6f-9c17-3773-882c-24232ad8eebd">
                <skos:member rdf:resource="http://localhost:8000/a1f23567-f9aa-3468-8692-940d672058fd"/>
                <skos:member rdf:resource="http://localhost:8000/4552d507-01f2-3f60-8a6a-e69558167ba3"/>
                <skos:member rdf:resource="http://localhost:8000/ef12e16f-87e8-3ad0-9c5d-1f26b8430862"/>
            </skos:Concept>
        </skos:member>
        <skos:member>
            <skos:Concept rdf:about="http://localhost:8000/5b4bd5d6-b35f-3c62-948c-a3f1f2d1162d">
                <skos:member rdf:resource="http://localhost:8000/9cc27e2b-e7bd-37b9-ad70-8cfd9d2cbc27"/>
                <skos:member rdf:resource="http://localhost:8000/59ba1d6e-9646-373f-b265-5f06dbccba6e"/>
            </skos:Concept>
        </skos:member>
    </skos:Concept>
    <skos:Concept rdf:about="http://localhost:8000/3c5e571d-e5f9-3d00-9954-4eebb82fba7d"/>
    <skos:Concept rdf:about="http://localhost:8000/6ba0df72-4fb9-3c63-965b-cfa4ff71da51"/>
    <skos:Concept rdf:about="http://localhost:8000/5c821208-0b0a-3ac6-9a39-1c29e1c331e1"/>
    <skos:Concept rdf:about="http://localhost:8000/b982a828-458b-3a2d-a7d0-cfcac0499ff7"/>
    <skos:Concept rdf:about="http://localhost:8000/8194e11a-1e8e-30fb-ab45-488579b9c094">
        <skos:member>
            <skos:Concept rdf:about="http://localhost:8000/a9df4a95-a384-355c-981b-940c7932e631"/>
        </skos:member>
        <skos:member>
            <skos:Concept rdf:about="http://localhost:8000/6f6ca3fd-02de-3554-ab4d-71d42b66f5f9"/>
        </skos:member>
        <skos:member>
            <skos:Concept rdf:about="http://localhost:8000/f9d11d26-0b33-3c4e-84d2-077733e36c3c"/>
        </skos:member>
        <skos:member>
            <skos:Concept rdf:about="http://localhost:8000/9023bced-2d3c-3ffa-8e3e-6339cb99c602"/>
        </skos:member>
    </skos:Concept>
    <skos:Concept rdf:about="http://localhost:8000/e70e3c47-2eec-309f-92b9-9c0c4f049ee4">
        <skos:member>
            <skos:Concept rdf:about="http://localhost:8000/f59c63a6-814b-3328-9484-f15c243c632c">
                <skos:member rdf:resource="http://localhost:8000/984b79ae-b0a5-3421-b398-f26418bb9022"/>
                <skos:member rdf:resource="http://localhost:8000/0bed8dee-c980-3d8d-be75-5adf1d6f9061"/>
                <skos:member rdf:resource="http://localhost:8000/19a6d1ee-e2c3-32fa-b05a-3a1a57f3ab6f"/>
            </skos:Concept>
        </skos:member>
        <skos:member>
            <skos:Concept rdf:about="http://localhost:8000/c40ceef3-3446-3e50-9ca2-5efe35eb6518">
                <skos:member rdf:resource="http://localhost:8000/5c821208-0b0a-3ac6-9a39-1c29e1c331e1"/>
                <skos:member rdf:resource="http://localhost:8000/91d8abe7-ec2c-359d-888f-10bcd02af527"/>
                <skos:member rdf:resource="http://localhost:8000/c73e1cf3-a347-3257-b172-c7811482b681"/>
                <skos:member rdf:resource="http://localhost:8000/2e96e243-34ac-357d-94ab-6ee26c698259"/>
            </skos:Concept>
        </skos:member>
        <skos:member>
            <skos:Concept rdf:about="http://localhost:8000/c5a5849a-b199-3357-b2ac-bfe1291bfeae">
                <skos:member rdf:resource="http://localhost:8000/6239b30e-24f4-3ef0-818c-cae527d0ae6a"/>
                <skos:member rdf:resource="http://localhost:8000/8619d06e-0da6-35c9-902d-534b75814c6b"/>
                <skos:member rdf:resource="http://localhost:8000/5a866b54-fa34-3619-9742-a498fa58630c"/>
            </skos:Concept>
        </skos:member>
    </skos:Concept>
    <skos:Concept rdf:about="http://localhost:8000/95bebcd8-e767-3959-9df4-6e4e5b0358ce">
        <skos:member>
            <skos:Concept rdf:about="http://localhost:8000/73c4c6d6-c47b-3846-b9a2-000872a6d999"/>
        </skos:member>
        <skos:member>
            <skos:Concept rdf:about="http://localhost:8000/6a44c892-a617-3246-a197-8c94d2321529"/>
        </skos:member>
    </skos:Concept>
    <skos:Concept rdf:about="http://localhost:8000/0fe6a9af-9ff2-3c53-9159-c0ebe00b4e2e">
        <skos:member>
            <skos:Concept rdf:about="http://localhost:8000/5ac786dc-48ce-3345-86ef-a403e8679c20"/>
        </skos:member>
        <skos:member>
            <skos:Concept rdf:about="http://localhost:8000/c3ca7ba8-d6cc-3702-8270-2fc743c5c9bd"/>
        </skos:member>
        <skos:member>
            <skos:Concept rdf:about="http://localhost:8000/2633eff3-ae40-328a-ac22-96cd2a2ae422"/>
        </skos:member>
    </skos:Concept>
    <skos:Concept rdf:about="http://localhost:8000/886ab740-4442-3ab1-a503-88c893bbb49d">
        <skos:member rdf:resource="http://localhost:8000/0fe6a9af-9ff2-3c53-9159-c0ebe00b4e2e"/>
        <skos:member>
            <skos:Concept rdf:about="http://localhost:8000/4f54c54b-92fd-327d-b726-aa2d58f7ef7c">
                <skos:member rdf:resource="http://localhost:8000/9d3ee26f-eca9-3417-bc99-b4eaeed31777"/>
                <skos:member rdf:resource="http://localhost:8000/dc087801-b745-3cba-b70a-a95177ac8723"/>
                <skos:member rdf:resource="http://localhost:8000/b36f0d43-1be1-3913-8b04-a87f0b376a8c"/>
                <skos:member rdf:resource="http://localhost:8000/ac620711-143c-3bbc-ab58-4946c7d8a7c3"/>
            </skos:Concept>
        </skos:member>
    </skos:Concept>
    <skos:Concept rdf:about="http://localhost:8000/d35f7c5e-da71-30de-bd65-537357758445">
        <skos:member>
            <skos:Concept rdf:about="http://localhost:8000/6dfa4c9a-ce21-3cea-bdf5-51293809f57d">
                <skos:member rdf:resource="http://localhost:8000/940a7ad6-f4ed-37bf-9602-fbd231935854"/>
                <skos:member rdf:resource="http://localhost:8000/0cc69824-55f6-3677-b3b1-d8069501612a"/>
            </skos:Concept>
        </skos:member>
        <skos:member>
            <skos:Concept rdf:about="http://localhost:8000/7b8ada30-a078-361a-bb59-5f6d76657c9c">
                <skos:member rdf:resource="http://localhost:8000/a8031c1b-3557-38df-a75c-821c36e4ab78"/>
                <skos:member rdf:resource="http://localhost:8000/2c144022-d076-32da-8f7c-9d320340a78d"/>
                <skos:member rdf:resource="http://localhost:8000/3c8ec872-4c75-398f-ac3d-668e5303b779"/>
                <skos:member rdf:resource="http://localhost:8000/725bf250-49cb-3fdc-ac64-b339863958e5"/>
                <skos:member rdf:resource="http://localhost:8000/639a64f6-7776-3e54-bc92-0404b1394c6d"/>
                <skos:member rdf:resource="http://localhost:8000/39a7de24-e22d-340a-bb4e-54daf33885e3"/>
            </skos:Concept>
        </skos:member>
    </skos:Concept>
    <skos:Concept rdf:about="http://localhost:8000/f6915b75-e754-3b32-9c71-024b9b873bdc">
        <skos:member>
            <skos:Concept rdf:about="http://localhost:8000/099e4794-0cd5-356b-8371-51ac3df3f339"/>
        </skos:member>
        <skos:member>
            <skos:Concept rdf:about="http://localhost:8000/0a9f0d50-ecd7-3e65-b0ac-cfac1d0aadb4"/>
        </skos:member>
        <skos:member>
            <skos:Concept rdf:about="http://localhost:8000/0196d93c-d4f1-3b9a-9d68-abbb99b14811"/>
        </skos:member>
    </skos:Concept>
    <skos:Concept rdf:about="http://localhost:8000/e4b2b248-ba9a-3f32-8e96-87ec23291798">
        <skos:member>
            <skos:Concept rdf:about="http://localhost:8000/a8fd9c4b-1706-3b58-95ff-57cda9348c6f">
                <skos:member rdf:resource="http://localhost:8000/38316b9c-18e9-3e08-821c-d7a21cc097a0"/>
                <skos:member rdf:resource="http://localhost:8000/6b2cb64a-f19f-3ca5-8d4f-384241478ef0"/>
                <skos:member rdf:resource="http://localhost:8000/bf0b3fef-c886-37ec-b1e4-848ca1791963"/>
            </skos:Concept>
        </skos:member>
        <skos:member>
            <skos:Concept rdf:about="http://localhost:8000/781ad3ff-3c26-39ff-b1e4-11bef5d4857a">
                <skos:member rdf:resource="http://localhost:8000/2c7eff16-498c-3e50-af31-3fca59795411"/>
                <skos:member rdf:resource="http://localhost:8000/355ab66b-6c3d-3103-a3da-3b295e4553e8"/>
                <skos:member rdf:resource="http://localhost:8000/d9f0c5b4-84d6-36d5-b2d3-dc6f3c72d847"/>
            </skos:Concept>
        </skos:member>
    </skos:Concept>
    <skos:Concept rdf:about="http://localhost:8000/d71d1937-4b4b-3988-964c-e910410f1dd8">
        <skos:member>
            <skos:Concept rdf:about="http://localhost:8000/961be967-f025-3067-a17c-8c9b05b10204"/>
        </skos:member>
        <skos:member>
            <skos:Concept rdf:about="http://localhost:8000/e23d08b4-68c1-3653-8384-b4a709bd4824"/>
        </skos:member>
        <skos:member>
            <skos:Concept rdf:about="http://localhost:8000/91599443-1b5a-3042-ac68-4ddbde390eb3"/>
        </skos:member>
    </skos:Concept>
    <skos:Concept rdf:about="http://localhost:8000/0ae8116f-366c-371c-bd6c-9e81ae1115e6"/>
    <skos:Concept rdf:about="http://localhost:8000/66b8f3c5-d948-300e-8ea7-9311fb5c2896"/>
    <skos:Concept rdf:about="http://localhost:8000/247af207-cbed-379c-80af-8367dfdaf835">
        <skos:member>
            <skos:Concept rdf:about="http://localhost:8000/626a252a-1e71-3b92-8e0a-5036c80c2163"/>
        </skos:member>
        <skos:member>
            <skos:Concept rdf:about="http://localhost:8000/2af907b4-49a4-34fa-9e38-93319f0b1d37"/>
        </skos:member>
    </skos:Concept>
    <skos:Concept rdf:about="http://localhost:8000/d9f0c5b4-84d6-36d5-b2d3-dc6f3c72d847">
        <skos:member>
            <skos:Concept rdf:about="http://localhost:8000/55da77ea-bbab-3b42-b00f-abb9ea328894"/>
        </skos:member>
        <skos:member>
            <skos:Concept rdf:about="http://localhost:8000/b4b5aa25-3631-3f16-97ab-5b08c1a7aa6e"/>
        </skos:member>
    </skos:Concept>
    <skos:Concept rdf:about="http://localhost:8000/84dd03ae-dbea-34f1-8159-58a717ff296e">
        <skos:member>
            <skos:Concept rdf:about="http://localhost:8000/d28e8b0e-96a0-3b91-abd0-8b4553e2dd46"/>
        </skos:member>
        <skos:member>
            <skos:Concept rdf:about="http://localhost:8000/241c5fe7-8e42-366d-8f5f-849c07cef39a"/>
        </skos:member>
        <skos:member rdf:resource="http://localhost:8000/66b8f3c5-d948-300e-8ea7-9311fb5c2896"/>
        <skos:member>
            <skos:Concept rdf:about="http://localhost:8000/30307164-994c-3790-ba54-238a707f96b4"/>
        </skos:member>
        <skos:member rdf:resource="http://localhost:8000/0ae8116f-366c-371c-bd6c-9e81ae1115e6"/>
        <skos:member>
            <skos:Concept rdf:about="http://localhost:8000/2a6d2c19-b5ae-383b-b8ef-2f7eb15dd8c2"/>
        </skos:member>
    </skos:Concept>
    <skos:Concept rdf:about="http://localhost:8000/5a866b54-fa34-3619-9742-a498fa58630c"/>
    <skos:Concept rdf:about="http://localhost:8000/71e98077-562d-3eef-a274-a1ff52edc14c"/>
    <skos:Concept rdf:about="http://localhost:8000/f1d37da1-2534-3184-a360-c716bff3982e">
        <skos:member rdf:resource="http://localhost:8000/d35f7c5e-da71-30de-bd65-537357758445"/>
        <skos:member rdf:resource="http://localhost:8000/886ab740-4442-3ab1-a503-88c893bbb49d"/>
        <skos:member>
            <skos:Concept rdf:about="http://localhost:8000/9c1e99bb-da95-30df-aef6-ac449c967d9b">
                <skos:member rdf:resource="http://localhost:8000/247af207-cbed-379c-80af-8367dfdaf835"/>
                <skos:member rdf:resource="http://localhost:8000/280edf0e-82ab-360e-b16b-7ce3587dd6bd"/>
                <skos:member rdf:resource="http://localhost:8000/37e66a65-a541-3f84-8ca1-2c029d93a8c0"/>
            </skos:Concept>
        </skos:member>
    </skos:Concept>
    <skos:Concept rdf:about="http://localhost:8000/85e7de80-225d-3a16-a694-2fbc6419f78e">
        <skos:member>
            <skos:Concept rdf:about="http://localhost:8000/f505ed39-3cee-3163-8a7e-acce8b703be4">
                <skos:member rdf:resource="http://localhost:8000/73cd9111-acc8-37ef-a7c8-a372048ab229"/>
                <skos:member rdf:resource="http://localhost:8000/59ed785a-4ba8-39b6-a3a8-864fd60016ac"/>
            </skos:Concept>
        </skos:member>
        <skos:member rdf:resource="http://localhost:8000/f6915b75-e754-3b32-9c71-024b9b873bdc"/>
        <skos:member>
            <skos:Concept rdf:about="http://localhost:8000/6ef94473-06f9-3f7d-ad1b-01b252170fcf">
                <skos:member rdf:resource="http://localhost:8000/08dfc338-f105-36ae-bd03-d050d6fdedd7"/>
                <skos:member rdf:resource="http://localhost:8000/d07ae5f2-858f-3112-8b7f-cb16e130519b"/>
            </skos:Concept>
        </skos:member>
    </skos:Concept>
    <skos:Concept rdf:about="http://localhost:8000/0c5e3acd-73d8-30a1-a6d5-9687669d694f">
        <skos:member rdf:resource="http://localhost:8000/b982a828-458b-3a2d-a7d0-cfcac0499ff7"/>
        <skos:member>
            <skos:Concept rdf:about="http://localhost:8000/95b16e88-1e55-3e0b-ab41-4aac484270b7"/>
        </skos:member>
        <skos:member>
            <skos:Concept rdf:about="http://localhost:8000/15f37f05-87db-33a7-9048-7e56493844f1"/>
        </skos:member>
    </skos:Concept>
    <skos:Concept rdf:about="http://localhost:8000/5e3c0df5-978a-3ee2-aa2f-ece9bdb0a61f"/>
    <skos:Concept rdf:about="http://localhost:8000/3f57fb2e-3d79-36cd-b001-b4dc5eb96238"/>
    <skos:Concept rdf:about="http://localhost:8000/fb547885-3bf0-3296-b740-dab5737ad571">
        <skos:member>
            <skos:Concept rdf:about="http://localhost:8000/b7dfb5b8-023b-3c93-8479-bf68bd0a3f6b"/>
        </skos:member>
        <skos:member>
            <skos:Concept rdf:about="http://localhost:8000/96c852f1-acba-39cb-a96e-db48cbbe010c"/>
        </skos:member>
        <skos:member>
            <skos:Concept rdf:about="http://localhost:8000/d248222f-e936-3221-8adc-081ac09435ec"/>
        </skos:member>
    </skos:Concept>
    <skos:Concept rdf:about="http://localhost:8000/08dfc338-f105-36ae-bd03-d050d6fdedd7"/>
    <skos:Concept rdf:about="http://localhost:8000/1111840f-f978-342f-812a-cea936ae0010">
        <skos:member rdf:resource="http://localhost:8000/0c5e3acd-73d8-30a1-a6d5-9687669d694f"/>
        <skos:member rdf:resource="http://localhost:8000/8194e11a-1e8e-30fb-ab45-488579b9c094"/>
        <skos:member>
            <skos:Concept rdf:about="http://localhost:8000/f2e5d20a-6a13-33f9-a222-36b8d6b92528">
                <skos:member rdf:resource="http://localhost:8000/866780f0-7c62-334f-9b2f-1c773d0b43df"/>
                <skos:member rdf:resource="http://localhost:8000/d4d9e69b-9d96-3514-8ff8-ba11d2dd7f3f"/>
                <skos:member rdf:resource="http://localhost:8000/cfde6ebc-9b6f-3d17-be1e-75373b641a24"/>
                <skos:member rdf:resource="http://localhost:8000/d060538f-cc75-34da-a242-150ecda0e92f"/>
            </skos:Concept>
        </skos:member>
    </skos:Concept>
    <skos:Concept rdf:about="http://localhost:8000/dc087801-b745-3cba-b70a-a95177ac8723"/>
    <skos:Concept rdf:about="http://localhost:8000/af277c18-03f8-34d2-a864-34b273a513d3">
        <skos:member>
            <skos:Concept rdf:about="http://localhost:8000/868b1bc8-6b36-3a4d-95bb-b3d8e562f7fc"/>
        </skos:member>
        <skos:member rdf:resource="http://localhost:8000/6ba0df72-4fb9-3c63-965b-cfa4ff71da51"/>
    </skos:Concept>
    <skos:Concept rdf:about="http://localhost:8000/da0a557f-d3d9-33e9-90dd-8b713010e217">
        <skos:member>
            <skos:Concept rdf:about="http://localhost:8000/a3d93e8a-93fe-3ecf-b9ca-1744102154e7"/>
        </skos:member>
        <skos:member>
            <skos:Concept rdf:about="http://localhost:8000/ef19ab71-4a0a-30b7-9d0d-315b3ee23ac6"/>
        </skos:member>
        <skos:member>
            <skos:Concept rdf:about="http://localhost:8000/6c8603cf-45f1-37fc-b4a8-a6b74bf430c1"/>
        </skos:member>
        <skos:member rdf:resource="http://localhost:8000/c63af19a-1b16-3059-82cb-2009204cecfa"/>
        <skos:member rdf:resource="http://localhost:8000/5e3c0df5-978a-3ee2-aa2f-ece9bdb0a61f"/>
        <skos:member>
            <skos:Concept rdf:about="http://localhost:8000/b30804d3-8d80-3b05-9e07-a95df77c43ba"/>
        </skos:member>
    </skos:Concept>
    <skos:Concept rdf:about="http://localhost:8000/0c4ae90e-dcf0-33be-80d1-675dc8b90e69">
        <skos:member>
            <skos:Concept rdf:about="http://localhost:8000/460c8303-e378-32cc-9393-e6185bde47be"/>
        </skos:member>
        <skos:member>
            <skos:Concept rdf:about="http://localhost:8000/bd5d04f8-77b9-334b-89cd-a4e783e4600c"/>
        </skos:member>
        <skos:member>
            <skos:Concept rdf:about="http://localhost:8000/562efa22-956a-3d9e-a9ae-df354f25a0fe"/>
        </skos:member>
    </skos:Concept>
    <skos:Concept rdf:about="http://localhost:8000/bf0b3fef-c886-37ec-b1e4-848ca1791963">
        <skos:member>
            <skos:Concept rdf:about="http://localhost:8000/9bb02f3f-6a59-3722-8288-ce27d1c61dde"/>
        </skos:member>
    </skos:Concept>
    <skos:Concept rdf:about="http://localhost:8000/b1fabadc-7863-3081-8f40-556579978f85">
        <skos:member rdf:resource="http://localhost:8000/6d509fcc-b642-39d2-8961-2d867c4b4560"/>
        <skos:member>
            <skos:Concept rdf:about="http://localhost:8000/e61d623f-eb7e-3de1-b2e9-d88a748bcd31">
                <skos:member rdf:resource="http://localhost:8000/2abc82f3-3362-3692-b17e-095a68ea1098"/>
                <skos:member rdf:resource="http://localhost:8000/c7d71520-14f6-3908-90e9-8b63263f2344"/>
                <skos:member rdf:resource="http://localhost:8000/553596fb-6290-33f6-a332-2b7f1fc812ba"/>
            </skos:Concept>
        </skos:member>
        <skos:member>
            <skos:Concept rdf:about="http://localhost:8000/09a199e2-9b25-35bd-a047-74fd1d03f8aa">
                <skos:member rdf:resource="http://localhost:8000/0c4ae90e-dcf0-33be-80d1-675dc8b90e69"/>
                <skos:member rdf:resource="http://localhost:8000/af277c18-03f8-34d2-a864-34b273a513d3"/>
                <skos:member rdf:resource="http://localhost:8000/b4e8d38b-433b-3083-bef6-ddb28586e04d"/>
            </skos:Concept>
        </skos:member>
        <skos:member rdf:resource="http://localhost:8000/e4b2b248-ba9a-3f32-8e96-87ec23291798"/>
        <skos:member>
            <skos:Concept rdf:about="http://localhost:8000/464d0766-8f90-3f4c-89ed-added46a7731">
                <skos:member rdf:resource="http://localhost:8000/b7beb6e6-230c-3a01-9f81-458ab5200210"/>
                <skos:member rdf:resource="http://localhost:8000/d71d1937-4b4b-3988-964c-e910410f1dd8"/>
                <skos:member rdf:resource="http://localhost:8000/c540d67a-e48a-367f-8fe3-dbcd9aa4fe6c"/>
                <skos:member rdf:resource="http://localhost:8000/b885e6f5-50c2-32bb-aa24-812e858f401f"/>
            </skos:Concept>
        </skos:member>
        <skos:member>
            <skos:Concept rdf:about="http://localhost:8000/c33e0447-6ded-34f1-8d87-b3b9f081dff4">
                <skos:member rdf:resource="http://localhost:8000/95bebcd8-e767-3959-9df4-6e4e5b0358ce"/>
                <skos:member rdf:resource="http://localhost:8000/3fbbd039-16ad-39cf-8286-ff279b9a9034"/>
                <skos:member rdf:resource="http://localhost:8000/fb547885-3bf0-3296-b740-dab5737ad571"/>
            </skos:Concept>
        </skos:member>
    </skos:Concept>
    <skos:Concept rdf:about="http://localhost:8000/37e66a65-a541-3f84-8ca1-2c029d93a8c0">
        <skos:member>
            <skos:Concept rdf:about="http://localhost:8000/53cb8aed-2c8d-3b8d-a875-329cb8eef2d9"/>
        </skos:member>
        <skos:member>
            <skos:Concept rdf:about="http://localhost:8000/513d973e-c10c-3a6c-89b6-bfad53003928"/>
        </skos:member>
        <skos:member>
            <skos:Concept rdf:about="http://localhost:8000/d5e067ea-73ab-3d2e-b5ba-bde1fc209525"/>
        </skos:member>
    </skos:Concept>
    <skos:Concept rdf:about="http://localhost:8000/2abc82f3-3362-3692-b17e-095a68ea1098">
        <skos:member rdf:resource="http://localhost:8000/71e98077-562d-3eef-a274-a1ff52edc14c"/>
        <skos:member>
            <skos:Concept rdf:about="http://localhost:8000/b07bc510-f7b4-3bf6-a19e-f3bbdf61ec0e"/>
        </skos:member>
        <skos:member>
            <skos:Concept rdf:about="http://localhost:8000/941fe7bb-db7c-3116-977c-732287b0ce25"/>
        </skos:member>
    </skos:Concept>
    <skos:Concept rdf:about="http://localhost:8000/c4c1bc77-6a95-3b2e-9ea0-2568d2ce2941">
        <skos:member rdf:resource="http://localhost:8000/84dd03ae-dbea-34f1-8159-58a717ff296e"/>
        <skos:member rdf:resource="http://localhost:8000/da0a557f-d3d9-33e9-90dd-8b713010e217"/>
    </skos:Concept>
    <skos:Concept rdf:about="http://localhost:8000/c4fd1c6e-45b4-3269-a4e0-84068546df11"/>
    <skos:Concept rdf:about="http://localhost:8000/b885e6f5-50c2-32bb-aa24-812e858f401f">
        <skos:member>
            <skos:Concept rdf:about="http://localhost:8000/a92e9b3a-38a9-3a2f-8c11-ab132762a829"/>
        </skos:member>
        <skos:member>
            <skos:Concept rdf:about="http://localhost:8000/f7e753d4-eb84-36d7-ac33-b9f65a588b29"/>
        </skos:member>
    </skos:Concept>
    <skos:Concept rdf:about="http://localhost:8000/26842550-baa1-34ad-bce3-f58f350a0af6">
        <skos:member rdf:resource="http://localhost:8000/c4c1bc77-6a95-3b2e-9ea0-2568d2ce2941"/>
        <skos:member rdf:resource="http://localhost:8000/85e7de80-225d-3a16-a694-2fbc6419f78e"/>
        <skos:member rdf:resource="http://localhost:8000/1111840f-f978-342f-812a-cea936ae0010"/>
    </skos:Concept>
    <skos:Concept rdf:about="http://localhost:8000/8d120cb4-9689-39f8-9a70-f6d284cdba4a"/>
    <skos:Concept rdf:about="http://localhost:8000/727972d8-0039-3cce-9416-c9f644950d7d"/>
    <skos:Concept rdf:about="http://localhost:8000/529f18f2-80cf-3170-a0d8-462f1ce9dab0"/>
    <skos:Concept rdf:about="http://localhost:8000/ae352fec-08d0-3f04-a8cb-8b47fc5897dd">
        <skos:member>
            <skos:Concept rdf:about="http://localhost:8000/96481201-b722-3297-b7e3-f8d115401a7c"/>
        </skos:member>
        <skos:member>
            <skos:Concept rdf:about="http://localhost:8000/e0d5fe3c-ad6d-302f-b182-a1366419f070"/>
        </skos:member>
        <skos:member>
            <skos:Concept rdf:about="http://localhost:8000/bd0ff334-8513-3177-b7e4-b75c266ad613"/>
        </skos:member>
        <skos:member rdf:resource="http://localhost:8000/3f57fb2e-3d79-36cd-b001-b4dc5eb96238"/>
    </skos:Concept>
    <skos:Concept rdf:about="http://localhost:8000/c540d67a-e48a-367f-8fe3-dbcd9aa4fe6c">
        <skos:member rdf:resource="http://localhost:8000/8d120cb4-9689-39f8-9a70-f6d284cdba4a"/>
        <skos:member>
            <skos:Concept rdf:about="http://localhost:8000/d3b44873-80e7-37d2-8793-f57a382c2bbe"/>
        </skos:member>
    </skos:Concept>
    <skos:Concept rdf:about="http://localhost:8000/355ab66b-6c3d-3103-a3da-3b295e4553e8">
        <skos:member>
            <skos:Concept rdf:about="http://localhost:8000/c3d03113-5c43-3a90-aa42-3e3281fd0b5b"/>
        </skos:member>
    </skos:Concept>
    <skos:Concept rdf:about="http://localhost:8000/6b2cb64a-f19f-3ca5-8d4f-384241478ef0">
        <skos:member>
            <skos:Concept rdf:about="http://localhost:8000/40a29c8d-8d6c-367a-aad0-90ad1daed3fa"/>
        </skos:member>
    </skos:Concept>
    <skos:Concept rdf:about="http://localhost:8000/ac620711-143c-3bbc-ab58-4946c7d8a7c3"/>
    <skos:Concept rdf:about="http://localhost:8000/c7d71520-14f6-3908-90e9-8b63263f2344">
        <skos:member rdf:resource="http://localhost:8000/a93e0e4b-6c50-301f-aa36-6645ad24b5cf"/>
        <skos:member>
            <skos:Concept rdf:about="http://localhost:8000/9efdd714-2c03-3638-bece-4e2bf14e56be"/>
        </skos:member>
    </skos:Concept>
    <skos:Concept rdf:about="http://localhost:8000/73cd9111-acc8-37ef-a7c8-a372048ab229"/>
    <skos:Concept rdf:about="http://localhost:8000/c73e1cf3-a347-3257-b172-c7811482b681"/>
    <skos:Concept rdf:about="http://localhost:8000/19a6d1ee-e2c3-32fa-b05a-3a1a57f3ab6f"/>
    <skos:Concept rdf:about="http://localhost:8000/d4d9e69b-9d96-3514-8ff8-ba11d2dd7f3f"/>
    <skos:Concept rdf:about="http://localhost:8000/d060538f-cc75-34da-a242-150ecda0e92f"/>
    <skos:Concept rdf:about="http://localhost:8000/9e28e238-39b5-3676-92d4-dc81ea646d02"/>
    <skos:Concept rdf:about="http://localhost:8000/9cc27e2b-e7bd-37b9-ad70-8cfd9d2cbc27"/>
    <skos:Concept rdf:about="http://localhost:8000/6239b30e-24f4-3ef0-818c-cae527d0ae6a"/>
    <skos:Concept rdf:about="http://localhost:8000/940a7ad6-f4ed-37bf-9602-fbd231935854"/>
    <skos:Concept rdf:about="http://localhost:8000/8b711f00-6dde-3ccc-b0b8-27477dfe4439"/>
    <skos:Concept rdf:about="http://localhost:8000/b4e8d38b-433b-3083-bef6-ddb28586e04d">
        <skos:member rdf:resource="http://localhost:8000/9e28e238-39b5-3676-92d4-dc81ea646d02"/>
        <skos:member rdf:resource="http://localhost:8000/3c5e571d-e5f9-3d00-9954-4eebb82fba7d"/>
    </skos:Concept>
    <skos:Concept rdf:about="http://localhost:8000/52b37454-26b6-30fc-8075-a7042e6f4b12"/>
    <skos:Concept rdf:about="http://localhost:8000/59ba1d6e-9646-373f-b265-5f06dbccba6e"/>
    <skos:Concept rdf:about="http://localhost:8000/a8031c1b-3557-38df-a75c-821c36e4ab78"/>
    <skos:Concept rdf:about="http://localhost:8000/280edf0e-82ab-360e-b16b-7ce3587dd6bd">
        <skos:member>
            <skos:Concept rdf:about="http://localhost:8000/091b7dbf-8716-388d-b57d-7f3f4c98b3e4"/>
        </skos:member>
        <skos:member rdf:resource="http://localhost:8000/727972d8-0039-3cce-9416-c9f644950d7d"/>
        <skos:member>
            <skos:Concept rdf:about="http://localhost:8000/ce9f427a-3944-39a0-aa0b-0a0182968586"/>
        </skos:member>
        <skos:member>
            <skos:Concept rdf:about="http://localhost:8000/e283c689-6442-3685-9b64-d95aad26910b"/>
        </skos:member>
    </skos:Concept>
    <skos:Concept rdf:about="http://localhost:8000/b36f0d43-1be1-3913-8b04-a87f0b376a8c"/>
    <skos:Concept rdf:about="http://localhost:8000/0cc69824-55f6-3677-b3b1-d8069501612a"/>
    <skos:Concept rdf:about="http://localhost:8000/b7beb6e6-230c-3a01-9f81-458ab5200210">
        <skos:member>
            <skos:Concept rdf:about="http://localhost:8000/e95bf562-0ba6-3c4e-865b-c98ee4246d9d"/>
        </skos:member>
        <skos:member>
            <skos:Concept rdf:about="http://localhost:8000/65163d50-6ffb-3542-bbdf-b9aebccb80f5"/>
        </skos:member>
        <skos:member>
            <skos:Concept rdf:about="http://localhost:8000/8f283211-8bbb-3527-9b86-78f543b00ee1"/>
        </skos:member>
    </skos:Concept>
    <skos:Concept rdf:about="http://localhost:8000/553596fb-6290-33f6-a332-2b7f1fc812ba">
        <skos:member>
            <skos:Concept rdf:about="http://localhost:8000/5b5259e2-453d-3ba5-ab3c-349c2c796725"/>
        </skos:member>
        <skos:member>
            <skos:Concept rdf:about="http://localhost:8000/98263c10-8759-3d8a-a07e-5915b1769357"/>
        </skos:member>
    </skos:Concept>
    <skos:Concept rdf:about="http://localhost:8000/3fbbd039-16ad-39cf-8286-ff279b9a9034">
        <skos:member rdf:resource="http://localhost:8000/c4fd1c6e-45b4-3269-a4e0-84068546df11"/>
        <skos:member rdf:resource="http://localhost:8000/52b37454-26b6-30fc-8075-a7042e6f4b12"/>
        <skos:member>
            <skos:Concept rdf:about="http://localhost:8000/6e0c89ed-ec05-3b8f-aa34-764a0ab7c3f3"/>
        </skos:member>
        <skos:member>
            <skos:Concept rdf:about="http://localhost:8000/f6912126-392f-357b-9d1a-5187e1eecd29"/>
        </skos:member>
    </skos:Concept>
    <skos:Concept rdf:about="http://localhost:8000/0bed8dee-c980-3d8d-be75-5adf1d6f9061"/>
    <skos:Concept rdf:about="http://localhost:8000/2e96e243-34ac-357d-94ab-6ee26c698259"/>
    <skos:Concept rdf:about="http://localhost:8000/2c7eff16-498c-3e50-af31-3fca59795411">
        <skos:member rdf:resource="http://localhost:8000/8b711f00-6dde-3ccc-b0b8-27477dfe4439"/>
    </skos:Concept>
    <skos:Concept rdf:about="http://localhost:8000/8581e5a7-08cf-3fc6-9f5c-54d0020718cd"/>
    <skos:Concept rdf:about="http://localhost:8000/725bf250-49cb-3fdc-ac64-b339863958e5"/>
    <skos:Concept rdf:about="http://localhost:8000/9d3ee26f-eca9-3417-bc99-b4eaeed31777"/>
    <skos:Concept rdf:about="http://localhost:8000/cfde6ebc-9b6f-3d17-be1e-75373b641a24"/>
    <skos:Concept rdf:about="http://localhost:8000/91d8abe7-ec2c-359d-888f-10bcd02af527"/>
    <skos:Concept rdf:about="http://localhost:8000/38316b9c-18e9-3e08-821c-d7a21cc097a0">
        <skos:member rdf:resource="http://localhost:8000/529f18f2-80cf-3170-a0d8-462f1ce9dab0"/>
    </skos:Concept>
    <skos:Concept rdf:about="http://localhost:8000/866780f0-7c62-334f-9b2f-1c773d0b43df"/>
    <skos:Concept rdf:about="http://localhost:8000/39a7de24-e22d-340a-bb4e-54daf33885e3"/>
    <skos:Concept rdf:about="http://localhost:8000/ef12e16f-87e8-3ad0-9c5d-1f26b8430862"/>
    <skos:Concept rdf:about="http://localhost:8000/8619d06e-0da6-35c9-902d-534b75814c6b"/>
    <skos:Concept rdf:about="http://localhost:8000/984b79ae-b0a5-3421-b398-f26418bb9022"/>
    <skos:Concept rdf:about="http://localhost:8000/4552d507-01f2-3f60-8a6a-e69558167ba3"/>
    <skos:Concept rdf:about="http://localhost:8000/59ed785a-4ba8-39b6-a3a8-864fd60016ac"/>
    <skos:Concept rdf:about="http://localhost:8000/2c144022-d076-32da-8f7c-9d320340a78d"/>
    <skos:Concept rdf:about="http://localhost:8000/18e4d5fe-955b-35b9-81f6-33bb14650f67"/>
    <skos:Concept rdf:about="http://localhost:8000/3c8ec872-4c75-398f-ac3d-668e5303b779"/>
    <skos:Concept rdf:about="http://localhost:8000/7298ffc8-23ed-3a8e-85a0-27efb08a361e"/>
    <skos:Concept rdf:about="http://localhost:8000/d07ae5f2-858f-3112-8b7f-cb16e130519b"/>
    <skos:Concept rdf:about="http://localhost:8000/a1f23567-f9aa-3468-8692-940d672058fd"/>
    <skos:Concept rdf:about="http://localhost:8000/639a64f6-7776-3e54-bc92-0404b1394c6d"/>
</rdf:RDF>
